Metadata-Version: 2.1
Name: bayeshist
Version: 0.2
Summary: Bayesian histograms for estimation of binary event rates
Home-page: https://github.com/dionhaefner/bayeshist
Author: Dion Häfner
Author-email: mail@dionhaefner.de
License: MIT
Platform: UNKNOWN
Requires-Python: >=3.6
License-File: LICENSE
